d0sl_compiler/__init__.py
d0sl_compiler-0.1.0.dist-info/METADATA
d0sl_compiler-0.1.0.dist-info/WHEEL
d0sl_compiler-0.1.0.dist-info/RECORD
