Metadata-Version: 2.1
Name: d0sl-compiler
Version: 0.1.0
Summary: A stub for d0sl interactions package
License: MIT
Author: Andrey Gumirov
Author-email: andreyt45@gmail.com
Requires-Python: >=3.10,<4.0
Classifier: License :: OSI Approved :: MIT License
Classifier: Programming Language :: Python :: 3
Classifier: Programming Language :: Python :: 3.10
Classifier: Programming Language :: Python :: 3.11
Classifier: Programming Language :: Python :: 3.12
